LICENSE
MANIFEST.in
README.md
requirements.txt
setup.cfg
setup.py
TCIF/__init__.py
TCIF/algorithms/__init__.py
TCIF/algorithms/utils.py
TCIF/classes/T_CIF.py
TCIF/classes/T_CIF_observation.py
TCIF/classes/T_CIF_space.py
TCIF/classes/T_CIF_time.py
TCIF/classes/__init__.py
TrajectoryIntervalForest.egg-info/PKG-INFO
TrajectoryIntervalForest.egg-info/SOURCES.txt
TrajectoryIntervalForest.egg-info/dependency_links.txt
TrajectoryIntervalForest.egg-info/requires.txt
TrajectoryIntervalForest.egg-info/top_level.txt