Metadata-Version: 2.1
Name: TrajectoryIntervalForest
Version: 0.0.1
Summary: Trajectory Interval Forest
Home-page: https://github.com/cri98li/TIF
Author: Cristiano Landi
Author-email: cristiano.landi@phd.unipi.it
License: BSD-Clause-2
Keywords: keyword1 keyword2 keyword3
Classifier: Development Status :: 4 - Beta
Classifier: Intended Audience :: Developers
Classifier: Topic :: Software Development :: Build Tools
Classifier: License :: OSI Approved :: BSD License
Classifier: Operating System :: POSIX :: Other
Classifier: Operating System :: MacOS
Classifier: Programming Language :: Python
Classifier: Programming Language :: Python :: 3
License-File: LICENSE
Requires-Dist: CaGeo
Requires-Dist: numpy
Requires-Dist: pandas
Requires-Dist: tqdm
Requires-Dist: pycatch22
Requires-Dist: joblib
Requires-Dist: scikit-learn
Requires-Dist: setuptools
Provides-Extra: flag
